freetempmail/__init__.py
freetempmail/freetempmail.py
freetempmail-1.0.4.dist-info/LICENSE
freetempmail-1.0.4.dist-info/METADATA
freetempmail-1.0.4.dist-info/WHEEL
freetempmail-1.0.4.dist-info/top_level.txt
freetempmail-1.0.4.dist-info/RECORD
