Metadata-Version: 2.1
Name: freetempmail
Version: 1.0.4
Summary: Temp-Mail.org API wrapper.
Home-page: https://github.com/DedInc/freetempmail
Author: Maehdakvan
Author-email: visitanimation@google.com
Project-URL: Bug Tracker, https://github.com/DedInc/freetempmail/issues
Classifier: Programming Language :: Python :: 3
Classifier: License :: OSI Approved :: MIT License
Classifier: Operating System :: OS Independent
Requires-Python: >=3.6
License-File: LICENSE
Requires-Dist: asyncio
Requires-Dist: pyppeteer
Requires-Dist: cloudscraper
